泛型
===

## 泛型擦除

Java 程序里的泛型信息，在 Java 虚拟机里全部都丢失了。这么做主要是为了兼容引入泛型之前的代码。
对于限定了继承类的泛型参数，经过类型擦除后，所有的泛型参数都将变成所限定的继承类。也就是说，Java 编译器将选取该泛型所能指代的所有类中层次最高的那个，作为替换泛型的类。

```
class GenericTest<T extends Number> {
  T foo(T t) {
    return t;
  }
}

```
举个例子，在上面这段 Java 代码中，定义了一个 T extends Number 的泛型参数。它所对应的字节码如下所示。可以看到，foo 方法的方法描述符所接收参数的类型以及返回类型都为 Number。方法描述符是 Java 虚拟机识别方法调用的目标方法的关键。

```
T foo(T);
  descriptor: (Ljava/lang/Number;)Ljava/lang/Number;
  flags: (0x0000)
  Code:
    stack=1, locals=2, args_size=2
       0: aload_1
       1: areturn
  Signature: (TT;)TT;

```

## 桥接
为了保证编译而成的 Java 字节码能够保留重写的语义，Java 编译器额外添加了一个桥接方法。该桥接方法在字节码层面重写了父类的方法，并将调用子类的方法。

```
class Merchant<T extends Customer> {
  public double actionPrice(T customer) {
    return 0.0d;
  }
}

class VIPOnlyMerchant extends Merchant<VIP> {
  @Override
  public double actionPrice(VIP customer) {
    return 0.0d;
  }
}

```

编译之后：

```
class VIPOnlyMerchant extends Merchant<VIP>
...
  public double actionPrice(VIP);
    descriptor: (LVIP;)D
    flags: (0x0001) ACC_PUBLIC
    Code:
         0: dconst_0
         1: dreturn

  public double actionPrice(Customer);
    descriptor: (LCustomer;)D
    flags: (0x1041) ACC_PUBLIC, ACC_BRIDGE, ACC_SYNTHETIC
    Code:
         0: aload_0
         1: aload_1
         2: checkcast class VIP
         5: invokevirtual actionPrice:(LVIP;)D
         8: dreturn

// 这个桥接方法等同于
public double actionPrice(Customer customer) {
  return actionPrice((VIP) customer);
}

```

VIPOnlyMerchant 类将包含一个桥接方法 actionPrice(Customer)，它重写了父类的同名同方法描述符的方法。该桥接方法将传入的 Customer 参数强制转换为 VIP 类型，再调用原本的 actionPrice(VIP) 方法。

--

```
class Merchant {
  public Number actionPrice(Customer customer) {
    return 0;
  }
}

class NaiveMerchant extends Merchant {
  @Override
  public Double actionPrice(Customer customer) {
    return 0.0D;
  }
}

```
背景： Double 继承自Number。

此处代码应不符合方法重写的定义，因为名字、参数相同，返回类型不相同。但如果返回类型像这样有继承关系，jvm也会生成桥接方法，进而使编译通过

## super 和 extends
* List<? extends T > 不能写入，可以读。因为不能确定子类型究竟是什么
* List<? super T > 不能读，可以写入。因为不知道超类究竟是什么
* 如果你想从一个数据类型里获取数据，使用 ? extends 通配符
* 如果你想把对象写入一个数据结构里，使用 ? super 通配符
* 如果你既想存，又想取，那就别用通配符。
* [说得好](https://stackoverflow.com/questions/2776975/how-can-i-add-to-list-extends-number-data-structures/2777297#2777297)
* [PECS：Producer Extends，Consumer Super](https://www.cnblogs.com/softidea/p/4106659.html)
